bakura_pkg/__init__.py
bakura_pkg/audio/__init__.py
bakura_pkg/audio/wiring.py
bakura_pkg/resources/__init__.py
bakura_pkg_topsyi-0.0.1.dist-info/LICENSE
bakura_pkg_topsyi-0.0.1.dist-info/METADATA
bakura_pkg_topsyi-0.0.1.dist-info/WHEEL
bakura_pkg_topsyi-0.0.1.dist-info/top_level.txt
bakura_pkg_topsyi-0.0.1.dist-info/RECORD
